_version.py
openmc_cell_segmenter/__init__.py
openmc_cell_segmenter/core.py
openmc_cell_segmenter-0.1.1.dist-info/LICENSE
openmc_cell_segmenter-0.1.1.dist-info/METADATA
openmc_cell_segmenter-0.1.1.dist-info/WHEEL
openmc_cell_segmenter-0.1.1.dist-info/top_level.txt
openmc_cell_segmenter-0.1.1.dist-info/RECORD
