Metadata-Version: 2.1
Name: openmc-cell-segmenter
Version: 0.1.1
Summary: todo
Author: The Openmc Cell Segmenter Development Team
Project-URL: Homepage, https://github.com/fusion-energy/openmc_cell_segmenter
Project-URL: Bug Tracker, https://github.com/fusion-energy/openmc_cell_segmenter/issues
Project-URL: Documentation, https://openmc_cell_segmenter.readthedocs.io
Keywords: python,geometry,openmc
Classifier: Programming Language :: Python :: 3
Classifier: License :: OSI Approved :: MIT License
Classifier: Operating System :: OS Independent
Requires-Python: >=3.8
License-File: LICENSE
Requires-Dist: numpy >=1.21.1
Provides-Extra: tests
Requires-Dist: pytest >=5.4.3 ; extra == 'tests'
